{"activeTab":"image","variables":[],"snapToGrid":true,"customColors":[],"previewSafeArea":0,"name":"Benji Cards","currentEditor":"29KVe5EtEeUdYZs1vwqClY5RmNz1","showGrid":true,"snapToZones":true,"cardSize":"Poker","id":"YjKAUxvqoF0y6kWlmxBM","snapSize":6,"hierarchyPanelWidth":300,"shared":false,"currentEditorSessionId":"n7vm3oyxnjd","layoutData":{"textDataKey":"","id":0,"style":{"textWrap":"wrap","borderRadius":"10px 10px 10px 10px","background":"rgba(255, 255, 255, 1)","backgroundPositionY":"50%","outlineOffset":"-3px","width":"240px","overflow":"hidden","outlineStyle":"solid","whiteSpaceCollapse":"break-spaces","height":"336px","top":0,"wordSpacing":"normal","left":0,"backgroundSize":"cover","backgroundPositionX":"50%","position":"relative","backgroundRepeat":"no-repeat","outlineWidth":"3px"},"isStatic":false,"text":"","imageFolder":"","allowTextSquash":false,"flipTextDivWithZone":false,"childZones":[{"image":"","toggleIfNoContent":false,"dexStyle":{"ct_DBaseline":"hanging","ct_inverted":false,"ct_dy":"0em","ct":false,"ct_startOffset":50},"type":"text","isCollapsed":false,"rotation":0,"allowTextShrink":true,"parentID":0,"flipTextDivWithZone":false,"childZones":[],"imageDataKey":"","style":{"textAlign":"left","paddingBottom":"6px","paddingRight":"6px","paddingTop":"6px","columnRuleColor":"rgba(0, 0, 0, 1)","columnFill":"auto","columnRuleWidth":"1px","boxShadow":" 0px 3px 5px rgb(0, 0, 0, 0.23),  3px 0px 5px rgb(0, 0, 0, 0.23),  3px 3px 5px rgb(0, 0, 0, 0.23)","columnGap":"10px","fontSize":"15px","left":"6px","alignItems":"flex-start","columnRuleStyle":"solid","width":"228px","outlineStyle":"solid","height":"102px","top":"216px","paddingLeft":"6px","columnCount":"unset","borderRadius":"8px 8px 8px 8px","background":"rgba(255, 255, 255, 1)"},"imageFolder":"","text":"<p>Actions: {icons/HAction.png}{icons/HAction.png}</p><p>{icons/HAction.png}: Deal 1 damage to any character or player.</p><p>3/3</p>","isStatic":false,"textDataKey":"cardtext","id":5},{"toggleIfNoContent":false,"image":"images/Benji.png","dexStyle":{"ct":false,"ct_dy":"0em","ct_startOffset":50,"ct_inverted":false,"ct_DBaseline":"hanging"},"allowTextShrink":false,"parentID":0,"rotation":0,"type":"image","isCollapsed":false,"childZones":[],"imageDataKey":"cardimage","flipTextDivWithZone":false,"text":"","isStatic":false,"imageFolder":"","style":{"height":"132px","outlineStyle":"solid","width":"228px","top":"48px","backgroundRepeat":"no-repeat","boxShadow":" 0px 1px 5px rgb(0, 0, 0, 0.31),  1px 0px 5px rgb(0, 0, 0, 0.31),  1px 1px 5px rgb(0, 0, 0, 0.31)","backgroundSize":"cover","left":"6px","backgroundPositionX":"50%","backgroundPositionY":"50%","borderRadius":"8px 8px 8px 8px"},"id":3,"textDataKey":""},{"image":"icons/HAction.png","toggleIfNoContent":false,"parentID":0,"allowTextShrink":false,"rotation":0,"type":"image","isCollapsed":false,"dexStyle":{"ct_startOffset":50,"ct_dy":"0em","ct":false,"ct_inverted":false,"ct_DBaseline":"hanging"},"childZones":[],"imageDataKey":"cardtypeimage","flipTextDivWithZone":false,"id":2,"textDataKey":"","text":"","isStatic":false,"imageFolder":"","style":{"backgroundSize":"contain","left":"198px","borderRadius":"46px 46px 46px 46px","backgroundPositionX":"50%","backgroundPositionY":"50%","backgroundRepeat":"no-repeat","top":"6px","boxShadow":" 0px 5px 5px rgb(0, 0, 0, 0.14),  5px 0px 5px rgb(0, 0, 0, 0.14),  5px 5px 5px rgb(0, 0, 0, 0.14)","width":"36px","height":"36px","outlineStyle":"solid"}},{"parentID":0,"allowTextShrink":true,"isCollapsed":false,"rotation":0,"type":"text","dexStyle":{"ct_inverted":false,"ct":false,"ct_dy":"0em","ct_startOffset":50,"ct_DBaseline":"hanging"},"image":"","toggleIfNoContent":false,"textDataKey":"cardname","id":1,"style":{"paddingRight":"9px","textAlign":"left","paddingBottom":"9px","columnFill":"auto","paddingTop":"9px","columnRuleColor":"rgba(0, 0, 0, 1)","boxShadow":" 0px 5px 5px rgb(0, 0, 0, 0.09),  5px 0px 5px rgb(0, 0, 0, 0.09),  5px 5px 5px rgb(0, 0, 0, 0.09)","columnRuleWidth":"1px","fontSize":"18px","columnGap":"10px","left":"6px","columnRuleStyle":"solid","height":"36px","outlineStyle":"solid","width":"186px","top":"6px","paddingLeft":"9px","columnCount":"unset","background":"rgba(255, 255, 255, 1)","borderRadius":"8px 8px 8px 8px"},"isStatic":false,"text":"<p>Card Name</p>","allowTextSquash":false,"imageFolder":"","flipTextDivWithZone":false,"imageDataKey":"","childZones":[]},{"isCollapsed":false,"rotation":0,"type":"text","allowTextShrink":true,"parentID":0,"dexStyle":{"ct_DBaseline":"hanging","ct_inverted":false,"ct_startOffset":50,"ct_dy":"0em","ct":false},"image":"","toggleIfNoContent":false,"textDataKey":"cardtype","id":4,"style":{"top":"186px","columnRuleStyle":"solid","width":"228px","outlineStyle":"solid","height":"24px","columnCount":"unset","borderRadius":"8px 8px 8px 8px","background":"rgba(255, 255, 255, 1)","paddingLeft":"3px","columnRuleWidth":"1px","boxShadow":" 0px 2px 5px rgba(0, 0, 0, 0.25),  2px 0px 5px rgba(0, 0, 0, 0.25),  2px 2px 5px rgba(0, 0, 0, 0.25)","paddingBottom":"3px","paddingRight":"3px","columnRuleColor":"rgba(0, 0, 0, 1)","paddingTop":"3px","textShadow":"none","columnFill":"auto","left":"6px","columnGap":"10px"},"imageFolder":"","isStatic":false,"text":"<p>Unique Character - Human Hero</p>","flipTextDivWithZone":false,"imageDataKey":"","childZones":[]},{"toggleIfNoContent":false,"image":"","rotation":0,"isCollapsed":false,"type":"text","allowTextShrink":false,"parentID":0,"openPalette":false,"dexStyle":{"ct_DBaseline":"hanging","ct":false,"ct_startOffset":50,"ct_dy":"0em","ct_inverted":false},"needToChooseLayoutType":false,"flipTextDivWithZone":false,"childZones":[],"imageDataKey":"","textDataKey":"rarity","id":8,"style":{"textWrap":"wrap","columnCount":"unset","columnRuleStyle":"solid","height":"12px","whiteSpaceCollapse":"break-spaces","width":"84px","color":"rgba(255, 255, 255, 1)","top":"318px","wordSpacing":"normal","fontSize":"8px","columnGap":"10px","left":"150px","textAlign":"right","columnFill":"auto","textShadow":"0em 0.010em 1em rgb(0, 0, 0, 0.64), 0.010em 0em 1em rgb(0, 0, 0, 0.64), 0.010em 0.010em 1em rgb(0, 0, 0, 0.64)","columnRuleColor":"rgba(0, 0, 0, 1)","backgroundRepeat":"no-repeat","columnRuleWidth":"1px"},"imageFolder":"","allowTextSquash":false,"text":"<p>Common</p>","isStatic":false},{"toggleIfNoContent":false,"image":"","type":"text","isCollapsed":false,"rotation":0,"parentID":0,"allowTextShrink":false,"needToChooseLayoutType":false,"openPalette":false,"dexStyle":{"ct_DBaseline":"hanging","ct_dy":"0em","ct":false,"ct_startOffset":50,"ct_inverted":false},"imageDataKey":"","childZones":[],"flipTextDivWithZone":false,"id":7,"textDataKey":"set name","allowTextSquash":false,"imageFolder":"","isStatic":false,"text":"<p>PROMO</p>","style":{"left":"96px","columnGap":"10px","fontSize":"8px","wordSpacing":"normal","columnRuleWidth":"1px","backgroundRepeat":"no-repeat","columnRuleColor":"rgba(0, 0, 0, 1)","textShadow":"0em 0.010em 1em rgb(0, 0, 0, 0.64), 0.010em 0em 1em rgb(0, 0, 0, 0.64), 0.010em 0.010em 1em rgb(0, 0, 0, 0.64)","columnFill":"auto","columnCount":"unset","textWrap":"wrap","top":"318px","width":"48px","color":"rgba(255, 255, 255, 1)","height":"12px","whiteSpaceCollapse":"break-spaces","columnRuleStyle":"solid"}},{"textDataKey":"card number","id":6,"style":{"columnGap":"10px","fontSize":"8px","left":"6px","textShadow":"0em 0.010em 1em rgb(0, 0, 0, 0.64), 0.010em 0em 1em rgb(0, 0, 0, 0.64), 0.010em 0.010em 1em rgb(0, 0, 0, 0.64)","columnRuleColor":"rgba(0, 0, 0, 1)","columnFill":"auto","textAlign":"left","columnRuleWidth":"1px","columnCount":"unset","color":"rgba(255, 255, 255, 1)","width":"48px","height":"12px","columnRuleStyle":"solid","top":"318px"},"isStatic":false,"text":"<p>1/1</p>","imageFolder":"","flipTextDivWithZone":false,"imageDataKey":"","childZones":[],"allowTextShrink":false,"parentID":0,"type":"text","rotation":0,"isCollapsed":false,"dexStyle":{"ct":false,"ct_startOffset":50,"ct_dy":"0em","ct_inverted":false,"ct_DBaseline":"hanging"},"toggleIfNoContent":false,"image":""}],"imageDataKey":"card_background","cardBaseName":"card_background","allowTextShrink":false,"parentID":null,"type":"image","isCollapsed":false,"rotation":0,"dexStyle":{"ct_DBaseline":"hanging","ct_dy":"0em","ct_startOffset":50,"ct":false,"ct_inverted":false},"openPalette":false,"needToChooseLayoutType":false,"image":"images/Background.png","toggleIfNoContent":false},"previewBleed":0,"openMenus":{"textMargin":false,"font":true,"transform":true,"textGlowShadow":false,"imageSetup":true,"textSetup":true,"effects":true,"layoutType":false,"boxShadow":true,"mixBlendMode":false,"textColor":true,"backgroundGradient":false,"zoneSize":false,"textAlignment":true,"letterSpacing":false,"cardSize":true,"individualCorners":false,"imageSizePosition":false,"lineHeight":false,"zonePosition":false,"backgroundColor":true,"border":true,"clipPath":true},"createdAt":{"type":"firestore/timestamp/1.0","seconds":1775170098,"nanoseconds":48000000},"lastUpdated":{"type":"firestore/timestamp/1.0","seconds":1775774762,"nanoseconds":887000000},"scale":1.8,"openPalette":false,"tags":[],"versionNum":58,"previewBleedAndSA":false,"needToChooseLayoutType":false,"showPalette":false}